tsdst/__init__.py
tsdst/distributions.py
tsdst/estimators.py
tsdst/feature_selection.py
tsdst/mcmc.py
tsdst/metrics.py
tsdst/modeling.py
tsdst/optimization.py
tsdst/parallel.py
tsdst/quick_analysis.py
tsdst/sampling.py
tsdst/tmath.py
tsdst/utils.py
tsdst-1.0.3.dist-info/LICENSE.txt
tsdst-1.0.3.dist-info/METADATA
tsdst-1.0.3.dist-info/WHEEL
tsdst-1.0.3.dist-info/top_level.txt
tsdst-1.0.3.dist-info/RECORD
