Metadata-Version: 2.1
Name: tsdst
Version: 1.0.3
Summary: A low-key data science and statistics toolkit
Home-page: https://tomwerner5.github.io/tsdst/
Author: Tom W
Author-email: tomwerner5@gmail.com
License: MIT
Download-URL: https://github.com/tomwerner5/tsdst/archive/v_1.0.3tar.gz
Keywords: data science,statistics,neural network,bayesian
Platform: UNKNOWN
Classifier: Development Status :: 3 - Alpha
Classifier: Intended Audience :: Science/Research
Classifier: Programming Language :: Python :: 3
Classifier: License :: OSI Approved :: MIT License
Classifier: Topic :: Scientific/Engineering :: Mathematics
Requires-Dist: matplotlib (>=3.1.0)
Requires-Dist: numba (>=0.44.1)
Requires-Dist: numdifftools (>=0.9.39)
Requires-Dist: numpy (>=1.16.4)
Requires-Dist: pandas (>=0.24.2)
Requires-Dist: scikit-learn (>=0.22.1)
Requires-Dist: scipy (>=1.2.1)
Requires-Dist: seaborn (>=0.11.0)
Requires-Dist: sqlalchemy (>=1.3.4)
Requires-Dist: statsmodels (>=0.9.0)
